MANIFEST.in
README.rst
setup.py
src/cornerstone/__init__.py
src/cornerstone.browser.egg-info/PKG-INFO
src/cornerstone.browser.egg-info/SOURCES.txt
src/cornerstone.browser.egg-info/dependency_links.txt
src/cornerstone.browser.egg-info/entry_points.txt
src/cornerstone.browser.egg-info/namespace_packages.txt
src/cornerstone.browser.egg-info/not-zip-safe
src/cornerstone.browser.egg-info/requires.txt
src/cornerstone.browser.egg-info/top_level.txt
src/cornerstone/browser/__init__.py
src/cornerstone/browser/base.py
src/cornerstone/browser/base.txt
src/cornerstone/browser/base.zcml
src/cornerstone/browser/configure.zcml
src/cornerstone/browser/exportimport.py
src/cornerstone/browser/form.py
src/cornerstone/browser/hotspot.py
src/cornerstone/browser/interfaces.py
src/cornerstone/browser/menu.py
src/cornerstone/browser/meta.zcml
src/cornerstone/browser/metaconfigure.py
src/cornerstone/browser/metadirectives.py
src/cornerstone/browser/overrides.zcml
src/cornerstone/browser/renderer.py
src/cornerstone/browser/tmpl.py
src/cornerstone/browser/tmpl.txt
src/cornerstone/browser/cornerstone_browser/cornerstone_hotspot.js
src/cornerstone/browser/examples/form/README.txt
src/cornerstone/browser/examples/form/__init__.py
src/cornerstone/browser/examples/form/configure.zcml
src/cornerstone/browser/examples/form/exampleform.pt
src/cornerstone/browser/examples/form/exampleform.py
src/cornerstone/browser/examples/form/exampleformview.pt
src/cornerstone/browser/js/cornerstone.ajax.js
src/cornerstone/browser/js/cornerstone.js
src/cornerstone/browser/js/jquery-1.2.6.js
src/cornerstone/browser/tests/__init__.py
src/cornerstone/browser/tests/test_base.py