Metadata-Version: 1.1
Name: cornerstone.browser
Version: 1.3.4
Summary: Common browser utils for ZOPE
Home-page: https://svn.plone.org/svn/collective/cornerstone.browser
Author: Robert Niederreiter
Author-email: rnix@squarewave.at
License: General Public Licence
Platform: UNKNOWN
Classifier: Development Status :: 5 - Production/Stable
Classifier: Environment :: Web Environment
Classifier: Framework :: Zope2
Classifier: License :: OSI Approved :: GNU General Public License (GPL)
Classifier: Operating System :: OS Independent
Classifier: Programming Language :: Python
Classifier: Topic :: Internet :: WWW/HTTP :: Dynamic Content
